qt_themes/__init__.py
qt_themes/_theme.py
qt_themes/themes/atom_one.json
qt_themes/themes/blender.json
qt_themes/themes/catppuccin_frappe.json
qt_themes/themes/catppuccin_latte.json
qt_themes/themes/catppuccin_macchiato.json
qt_themes/themes/catppuccin_mocha.json
qt_themes/themes/dracula.json
qt_themes/themes/github_dark.json
qt_themes/themes/github_light.json
qt_themes/themes/modern_dark.json
qt_themes/themes/modern_light.json
qt_themes/themes/monokai.json
qt_themes/themes/nord.json
qt_themes/themes/one_dark_two.json
qt_themes-0.4.0.dist-info/licenses/LICENSE
qt_themes-0.4.0.dist-info/METADATA
qt_themes-0.4.0.dist-info/WHEEL
qt_themes-0.4.0.dist-info/top_level.txt
qt_themes-0.4.0.dist-info/RECORD
