Metadata-Version: 2.4
Name: qt-themes
Version: 0.4.0
Summary: A collection of themes for Qt applications in Python.
Author: Beat Reichenbach
License-Expression: MIT
Requires-Python: >=3.9
License-File: LICENSE
Provides-Extra: dev
Requires-Dist: black>=24.0; extra == "dev"
Requires-Dist: python-semantic-release>=9.0; extra == "dev"
Requires-Dist: PySide6; extra == "dev"
Provides-Extra: pyside2
Requires-Dist: PySide2; extra == "pyside2"
Provides-Extra: pyside6
Requires-Dist: PySide6; extra == "pyside6"
Provides-Extra: qtpy
Requires-Dist: qtpy<3,>=2.0; extra == "qtpy"
Dynamic: license-file
